trackerpkg/__init__.py
trackerpkg/pkg.py
trackerpkg-1.0.0.dist-info/METADATA
trackerpkg-1.0.0.dist-info/WHEEL
trackerpkg-1.0.0.dist-info/top_level.txt
trackerpkg-1.0.0.dist-info/RECORD
